utm_epsg_finder/__init__.py
utm_epsg_finder/cli.py
utm_epsg_finder/utm_epsg_finder.py
utm_epsg_finder-0.2.1.dist-info/entry_points.txt
utm_epsg_finder-0.2.1.dist-info/LICENSE.rst
utm_epsg_finder-0.2.1.dist-info/WHEEL
utm_epsg_finder-0.2.1.dist-info/METADATA
utm_epsg_finder-0.2.1.dist-info/RECORD
