Metadata-Version: 2.1
Name: utm-epsg-finder
Version: 0.2.1
Summary: Python Boilerplate contains all the boilerplate you need to create a modern Python package.
Home-page: https://github.com/GIS-Consultant/utm-epsg-finder
Keywords: utm-epsg-finder
Author: Massimiliano Moraca
Author-email: info@massimilianomoraca.it
Requires-Python: >=3.6.1,<3.10
Classifier: Development Status :: 2 - Pre-Alpha
Classifier: Intended Audience :: Developers
Classifier: License :: OSI Approved :: MIT License
Classifier: Natural Language :: English
Classifier: Programming Language :: Python :: 3
Classifier: Programming Language :: Python :: 3.6
Classifier: Programming Language :: Python :: 3.7
Classifier: Programming Language :: Python :: 3.8
Classifier: Programming Language :: Python :: 3.9
Requires-Dist: click (>=7.1.2,<8.0.0)
Requires-Dist: geopandas (>=0.8.2,<0.9.0)
Requires-Dist: pathlib (>=1.0.1,<2.0.0)
Requires-Dist: pyproj (>=3.0.0,<4.0.0)
Requires-Dist: rasterio (>=1.2.1,<2.0.0)
Requires-Dist: twine (>=3.3.0,<4.0.0)
Requires-Dist: utm (>=0.7.0,<0.8.0)
Project-URL: Bug Tracker, https://github.com/GIS-Consultant/utm-epsg-finder/issues
Project-URL: Documentation, https://utm-epsg-finder.readthedocs.io
Project-URL: Repository, https://github.com/GIS-Consultant/utm-epsg-finder
